marv/__init__.py
marv/cli.py
marv/collection.py
marv/config.py
marv/db.py
marv/helpers.py
marv/model.py
marv/model_fields.py
marv/sexp.py
marv/site.py
marv/testing.py
marv/utils.py
marv/app/__init__.py
marv/app/docs/.buildinfo
marv/app/docs/CHANGES.html
marv/app/docs/CONTRIBUTING.html
marv/app/docs/accesscontrol.html
marv/app/docs/config.html
marv/app/docs/debug.html
marv/app/docs/deploy.html
marv/app/docs/genindex.html
marv/app/docs/httpapi.html
marv/app/docs/index.html
marv/app/docs/maintenance.html
marv/app/docs/nodes.html
marv/app/docs/objects.inv
marv/app/docs/patterns.html
marv/app/docs/py-modindex.html
marv/app/docs/scan.html
marv/app/docs/search.html
marv/app/docs/searchindex.js
marv/app/docs/upload.html
marv/app/docs/views.html
marv/app/docs/widgets.html
marv/app/docs/_modules/index.html
marv/app/docs/_modules/marv_api/decorators.html
marv/app/docs/_modules/marv_api/ioctrl.html
marv/app/docs/_modules/marv_robotics/bag.html
marv/app/docs/_modules/marv_robotics/cam.html
marv/app/docs/_modules/marv_robotics/detail.html
marv/app/docs/_modules/marv_robotics/fulltext.html
marv/app/docs/_modules/marv_robotics/gnss.html
marv/app/docs/_modules/marv_robotics/trajectory.html
marv/app/docs/_sources/CHANGES.rst.txt
marv/app/docs/_sources/CONTRIBUTING.rst.txt
marv/app/docs/_sources/accesscontrol.rst.txt
marv/app/docs/_sources/config.rst.txt
marv/app/docs/_sources/debug.rst.txt
marv/app/docs/_sources/deploy.rst.txt
marv/app/docs/_sources/httpapi.rst.txt
marv/app/docs/_sources/index.rst.txt
marv/app/docs/_sources/maintenance.rst.txt
marv/app/docs/_sources/nodes.rst.txt
marv/app/docs/_sources/patterns.rst.txt
marv/app/docs/_sources/scan.rst.txt
marv/app/docs/_sources/upload.rst.txt
marv/app/docs/_sources/views.rst.txt
marv/app/docs/_sources/widgets.rst.txt
marv/app/docs/_sources/api/marv.rst.txt
marv/app/docs/_sources/install/docker.rst.txt
marv/app/docs/_sources/install/index.rst.txt
marv/app/docs/_sources/install/native.rst.txt
marv-21.12.0.dist-info/LICENSE.txt
marv-21.12.0.dist-info/METADATA
marv-21.12.0.dist-info/WHEEL
marv-21.12.0.dist-info/entry_points.txt
marv-21.12.0.dist-info/top_level.txt
marv-21.12.0.dist-info/RECORD
